{
    "apiVersion": "v1beta1",
    "creationTimestamp": "2014-09-10T22:17:34-04:00",
    "description": "Example shows how to build a simple multi-tier application using Kubernetes and Docker",
    "id": "guestbook",
    "items": [
        {
            "apiVersion": "v1beta1",
            "containerPort": 0,
            "creationTimestamp": null,
            "id": "frontend",
            "kind": "Service",
            "port": 5432,
            "selector": {
                "name": "frontend"
            }
        },
        {
            "apiVersion": "v1beta1",
            "containerPort": 0,
            "creationTimestamp": null,
            "id": "redismaster",
            "kind": "Service",
            "port": 10000,
            "selector": {
                "name": "redis-master"
            }
        },
        {
            "apiVersion": "v1beta1",
            "containerPort": 0,
            "creationTimestamp": null,
            "id": "redisslave",
            "kind": "Service",
            "labels": {
                "name": "redisslave"
            },
            "port": 10001,
            "selector": {
                "name": "redisslave"
            }
        },
        {
            "apiVersion": "v1beta1",
            "creationTimestamp": null,
            "currentState": {
                "manifest": {
                    "containers": null,
                    "id": "",
                    "version": "",
                    "volumes": null
                },
                "restartpolicy": {}
            },
            "desiredState": {
                "manifest": {
                    "containers": [
                        {
                            "env": [
                                {
                                    "key": "REDIS_PASSWORD",
                                    "name": "REDIS_PASSWORD",
                                    "value": "LdldNM2P"
                                }
                            ],
                            "image": "dockerfile/redis",
                            "name": "master",
                            "ports": [
                                {
                                    "containerPort": 6379,
                                    "protocol": "TCP"
                                }
                            ]
                        }
                    ],
                    "id": "redis-master-2",
                    "version": "v1beta1",
                    "volumes": null
                },
                "restartpolicy": {
                    "type": "RestartAlways"
                }
            },
            "id": "redis-master-2",
            "kind": "Pod",
            "labels": {
                "name": "redis-master"
            }
        },
        {
            "apiVersion": "v1beta1",
            "creationTimestamp": null,
            "desiredState": {
                "podTemplate": {
                    "desiredState": {
                        "manifest": {
                            "containers": [
                                {
                                    "env": [
                                        {
                                            "key": "ADMIN_USERNAME",
                                            "name": "ADMIN_USERNAME",
                                            "value": "adminIHF"
                                        },
                                        {
                                            "key": "ADMIN_PASSWORD",
                                            "name": "ADMIN_PASSWORD",
                                            "value": "jWhka1FL"
                                        },
                                        {
                                            "key": "REDIS_PASSWORD",
                                            "name": "REDIS_PASSWORD",
                                            "value": "LdldNM2P"
                                        }
                                    ],
                                    "image": "brendanburns/php-redis",
                                    "name": "php-redis",
                                    "ports": [
                                        {
                                            "containerPort": 80,
                                            "hostPort": 8000,
                                            "protocol": "TCP"
                                        }
                                    ]
                                }
                            ],
                            "id": "frontendController",
                            "version": "v1beta1",
                            "volumes": null
                        },
                        "restartpolicy": {}
                    },
                    "labels": {
                        "name": "frontend"
                    }
                },
                "replicaSelector": {
                    "name": "frontend"
                },
                "replicas": 1
            },
            "id": "frontendController",
            "kind": "ReplicationController",
            "labels": {
                "name": "frontend"
            }
        },
        {
            "apiVersion": "v1beta1",
            "creationTimestamp": null,
            "desiredState": {
                "podTemplate": {
                    "desiredState": {
                        "manifest": {
                            "containers": [
                                {
                                    "env": [
                                        {
                                            "key": "REDIS_PASSWORD",
                                            "name": "REDIS_PASSWORD",
                                            "value": "LdldNM2P"
                                        }
                                    ],
                                    "image": "brendanburns/redis-slave",
                                    "name": "slave",
                                    "ports": [
                                        {
                                            "containerPort": 6379,
                                            "hostPort": 6380,
                                            "protocol": "TCP"
                                        }
                                    ]
                                }
                            ],
                            "id": "redisSlaveController",
                            "version": "v1beta1",
                            "volumes": null
                        },
                        "restartpolicy": {}
                    },
                    "labels": {
                        "name": "redisslave"
                    }
                },
                "replicaSelector": {
                    "name": "redisslave"
                },
                "replicas": 1
            },
            "id": "redisSlaveController",
            "kind": "ReplicationController",
            "labels": {
                "name": "redisslave"
            }
        }
    ],
    "kind": "Config",
    "name": "guestbook-example"
}
